{
  "card_result": [
    {
      "card_id": 13,
      "card_name": "A Morte",
      "card_revelation": "O véu ou máscara da vida se perpetuou em mudanças, transformações e passagens do inferior para o superior, e isso é melhor representado no Tarô retificado por uma das visões apocalípticas do que pela crua noção de esqueletos ceifadores. Atrás disso jaz todo o mundo de ascensão no espírito. O cavaleiro misterioso move-se devagar, trazendo uma bandeira negra com o brasão da Rosa Mística, que significa vida. Entre duas colunas, na orla do horizonte, brilha o sol da imortalidade. O cavaleiro não traz qualquer arma visível, mas o rei, o filho e a donzela caem diante dele, enquanto um prelado, de mãos postas, espera o seu fim. Não é preciso salientar que a sugestão da morte que apresentei relacionada com a carta anterior tem, sem sombra de dúvida, de ser compreendida misticamente , mas não é esse o caso no presente exemplo. A natural passagem do homem para o próximo estágio de seu ser é ou pode ser uma forma de seu progresso, mas a estranha e quase desconhecida admissão, enquanto ainda nesta vida, no estado de morte mística constitui uma mudança na forma de consciência e a passagem para o qual a morte ordinária não é o caminho nem a porta. As explicações ocultistas existentes da décima terceira carta são, em seu conjunto, melhores que as habituais, renascimento, criação, destino, renovação e repouso.",     
      "card_divination_meaning": " ",
      "card_divination_opposite": " ", 
      "card_image_path": "/pt/cards/13.png"
    }
  ]
}
