{
  "card_result": [
    {
      "card_id": 48,
      "card_name": "Dama de Ouros",
      "card_revelation": "O rosto é o de uma mulher cujas qualidades podem ser resumidas na idéia de grandeza da alma; tem também viva a expressão de inteligência; contempla o símbolo e nele pode ver diversos mundos.",     
      "card_divination_meaning": "Opulência, generosidade, magnificência, segurança, liberdade.",
      "card_divination_opposite": "Mal, suspeita, suspensão, temor, desconfiança.", 
      "card_image_path": "/pt/cards/48.png"
    }
  ]
}
